{
  "_fv": 13,
  "_type": "recipe",
  "definition": {
    "recipeType": "Crafting",
    "xpReward": 0.0,
    "cookingTime": 200,
    "recipeRetstackSize": 1,
    "group": "void_pouch",
    "recipeShapeless": false,
    "recipeSlots": [
      {
        "value": "Items.SHULKER_SHELL"
      },
      {
        "value": "Blocks.OBSIDIAN"
      },
      {
        "value": "Items.SHULKER_SHELL"
      },
      {
        "value": "Blocks.OBSIDIAN"
      },
      {
        "value": "Blocks.ENDER_CHEST"
      },
      {
        "value": "Blocks.OBSIDIAN"
      },
      {
        "value": "Items.SHULKER_SHELL"
      },
      {
        "value": "Blocks.OBSIDIAN"
      },
      {
        "value": "Items.SHULKER_SHELL"
      }
    ],
    "recipeReturnStack": {
      "value": "CUSTOM:VoudPouch"
    },
    "name": "void_pouch",
    "namespace": "mod"
  }
}